LICENSE
README.md
setup.py
supertld/AsymToSym.py
supertld/KR_norm_juicer.py
supertld/MultichildTree.py
supertld/SImi_tad.py
supertld/__init__.py
supertld/distance_decay.py
supertld/enrichment_boun_foldchange.py
supertld/enrichment_tad.py
supertld/evaluation.py
supertld/main.py
supertld/utils.py
supertld.egg-info/PKG-INFO
supertld.egg-info/SOURCES.txt
supertld.egg-info/dependency_links.txt
supertld.egg-info/top_level.txt
supertld/smurf/__init__.py
supertld/smurf/cell_circle.py
supertld/smurf/distance.py
supertld/smurf/initialParams.py
supertld/smurf/lossFunc.py
supertld/smurf/lossFunc_sym.py
supertld/smurf/model.py
supertld/smurf/model_sym.py
supertld/smurf/optimize.py
supertld/smurf/utiles.py
supertld/smurf/version.py