Metadata-Version: 2.1
Name: supertld
Version: 0.0.2
Summary: SuperTLD: Detecting TAD-like domains from RNA-associated interactions
Home-page: https://github.com/deepomicslab/SuperTLD
Author: Yu Wei Zhang
Author-email: ywzhang224@gmail.com
License: MIT
Platform: UNKNOWN
Classifier: License :: OSI Approved :: MIT License
Classifier: Programming Language :: Python :: 3
License-File: LICENSE
